oar_lib-0.4.1.dist-info/WHEEL
oar_lib-0.4.1.dist-info/DESCRIPTION.rst
oar_lib-0.4.1.dist-info/metadata.json
oar_lib-0.4.1.dist-info/top_level.txt
oar_lib-0.4.1.dist-info/RECORD
oar_lib-0.4.1.dist-info/METADATA
oar_lib/utils.py
oar_lib/globals.py
oar_lib/fixture.py
oar_lib/__init__.py
oar_lib/configuration.py
oar_lib/compat.py
oar_lib/basequery.py
oar_lib/models.py
oar_lib/psycopg2.py
oar_lib/exceptions.py
oar_lib/logging.py
oar_lib/database.py
oar/__init__.py
