Metadata-Version: 2.0
Name: oar-lib
Version: 0.4.1
Summary: Python version of OAR Common Library
Home-page: https://github.com/oar-team/python-oar-lib
Author: Salem Harrache
Author-email: salem.harrache@inria.fr
License: BSD
Keywords: oar-lib
Platform: UNKNOWN
Classifier: Development Status :: 4 - Beta
Classifier: License :: OSI Approved :: BSD License
Classifier: Intended Audience :: Developers
Classifier: Natural Language :: English
Classifier: Programming Language :: Python :: 2
Classifier: Programming Language :: Python :: 3
Classifier: Programming Language :: Python :: Implementation :: CPython
Classifier: Programming Language :: Python :: Implementation :: PyPy
Classifier: Topic :: Software Development :: Libraries :: Python Modules
Classifier: Topic :: System :: Clustering
Requires-Dist: sqlalchemy
Requires-Dist: alembic
